README.md
setup.py
./japanese_numbers/__init__.py
./japanese_numbers/kind.py
./japanese_numbers/result.py
./japanese_numbers/token.py
./japanese_numbers/parser/__init__.py
./japanese_numbers/parser/to_arabic_parser.py
japanese_numbers_python.egg-info/PKG-INFO
japanese_numbers_python.egg-info/SOURCES.txt
japanese_numbers_python.egg-info/dependency_links.txt
japanese_numbers_python.egg-info/requires.txt
japanese_numbers_python.egg-info/top_level.txt
japanese_numbers_python.egg-info/zip-safe